pydotmap/__init__.py
pydotmap/_version.py
pydotmap/pymap.py
pydotmap-0.1.3.dist-info/LICENSE
pydotmap-0.1.3.dist-info/METADATA
pydotmap-0.1.3.dist-info/WHEEL
pydotmap-0.1.3.dist-info/top_level.txt
pydotmap-0.1.3.dist-info/RECORD
