Metadata-Version: 2.1
Name: pydotmap
Version: 0.1.3
Summary: Dot notation python dicationary
Home-page: https://github.com/iamatulsingh/pydotmap
Author: Atul Singh
Author-email: atulsingh0401@gmail.com
License: UNKNOWN
Platform: UNKNOWN
Classifier: Programming Language :: Python :: 3
Classifier: License :: OSI Approved :: MIT License
Classifier: Operating System :: OS Independent
Requires-Python: >=3.6
